entropica_qaoa/__init__.py
entropica_qaoa/utilities.py
entropica_qaoa/qaoa/__init__.py
entropica_qaoa/qaoa/_parameter_conversions.py
entropica_qaoa/qaoa/cost_function.py
entropica_qaoa/qaoa/parameters.py
entropica_qaoa/vqe/__init__.py
entropica_qaoa/vqe/cost_function.py
entropica_qaoa/vqe/measurelib.py
entropica_qaoa-1.2.dist-info/LICENSE
entropica_qaoa-1.2.dist-info/METADATA
entropica_qaoa-1.2.dist-info/WHEEL
entropica_qaoa-1.2.dist-info/top_level.txt
entropica_qaoa-1.2.dist-info/RECORD
