Metadata-Version: 2.1
Name: entropica-qaoa
Version: 1.2
Summary: Entropica Labs QAOA package
Home-page: https://docs.entropicalabs.io/qaoa/
Author: Entropica Labs: Jan Lukas Bosse, Ewan Munro
Author-email: janlukas@entropicalabs.com, ewan@entropicalabs.com
License: UNKNOWN
Platform: UNKNOWN
Requires-Dist: scipy (>=0.9)
Requires-Dist: pyquil (>=2.0)
Requires-Dist: custom-inherit (>=2.0)
Requires-Dist: pandas (>=0.25)
Requires-Dist: matplotlib (>=3.0)
